[{"hidden_layer_size": 32, "batch": 32, "epoch": 200, "test_loss": 0.38, "test_accuracy": 0.772}, {"hidden_layer_size": 32, "batch": 64, "epoch": 200, "test_loss": 0.75, "test_accuracy": 0.469}, {"hidden_layer_size": 32, "batch": 64, "epoch": 200, "test_loss": 0.37, "test_accuracy": 0.795}, {"hidden_layer_size": 32, "batch": 64, "epoch": 200, "test_loss": 0.37, "test_accuracy": 0.797}, {"hidden_layer_size": 32, "batch": 64, "epoch": 200, "test_loss": 0.39, "test_accuracy": 0.788}, {"hidden_layer_size": 32, "batch": 64, "epoch": 200, "test_loss": 0.37, "test_accuracy": 0.786}, {"hidden_layer_size": 32, "batch": 64, "epoch": 200, "test_loss": 0.38, "test_accuracy": 0.795}, {"hidden_layer_size": 32, "batch": 64, "epoch": 200, "test_loss": 0.37, "test_accuracy": 0.792}, {"hidden_layer_size": 32, "batch": 64, "epoch": 200, "test_loss": 0.39, "test_accuracy": 0.792}, {"hidden_layer_size": 32, "batch": 64, "epoch": 200, "test_loss": 0.38, "test_accuracy": 0.801}, {"hidden_layer_size": 64, "batch": 64, "epoch": 200, "test_loss": 0.37, "test_accuracy": 0.804}, {"hidden_layer_size": 64, "batch": 64, "epoch": 200, "test_loss": 0.38, "test_accuracy": 0.795}, {"hidden_layer_size": 64, "batch": 64, "epoch": 200, "test_loss": 0.38, "test_accuracy": 0.788}, {"hidden_layer_size": 64, "batch": 64, "epoch": 200, "test_loss": 0.37, "test_accuracy": 0.795}]